<annotation>
	<folder></folder>
	<filename>845_jpg.rf.5afba6d44499dd1ae530cb61f3f77a14.jpg</filename>
	<path>845_jpg.rf.5afba6d44499dd1ae530cb61f3f77a14.jpg</path>
	<source>
		<database>roboflow.ai</database>
	</source>
	<size>
		<width>161</width>
		<height>158</height>
		<depth>3</depth>
	</size>
	<segmented>0</segmented>
	<object>
		<name>goat</name>
		<pose>Unspecified</pose>
		<truncated>0</truncated>
		<difficult>0</difficult>
		<occluded>0</occluded>
		<bndbox>
			<xmin>1</xmin>
			<xmax>82</xmax>
			<ymin>91</ymin>
			<ymax>155</ymax>
		</bndbox>
	</object>
	<object>
		<name>person</name>
		<pose>Unspecified</pose>
		<truncated>0</truncated>
		<difficult>0</difficult>
		<occluded>0</occluded>
		<bndbox>
			<xmin>31</xmin>
			<xmax>76</xmax>
			<ymin>1</ymin>
			<ymax>152</ymax>
		</bndbox>
	</object>
</annotation>
