<annotation>
  <folder>adit</folder>
  <filename>adit_mp4-614_jpg.rf.c0f2d01124c05431051487b1d0f4ee2c.jpg</filename>
  <source>
    <database>Unknown</database>
    <annotation>Unknown</annotation>
    <image>Unknown</image>
  </source>
  <size>
    <width>640</width>
    <height>480</height>
    <depth></depth>
  </size>
  <segmented>0</segmented>
  <object>
    <name>car</name>
    <truncated>0</truncated>
    <occluded>0</occluded>
    <difficult>0</difficult>
    <bndbox>
      <xmin>303.21</xmin>
      <ymin>199.51</ymin>
      <xmax>337.59</xmax>
      <ymax>235.12</ymax>
    </bndbox>
    <attributes>
      <attribute>
        <name>rotation</name>
        <value>0.0</value>
      </attribute>
    </attributes>
  </object>
  <object>
    <name>truck-m-</name>
    <truncated>0</truncated>
    <occluded>0</occluded>
    <difficult>0</difficult>
    <bndbox>
      <xmin>532.16</xmin>
      <ymin>249.26</ymin>
      <xmax>640.0</xmax>
      <ymax>381.88</ymax>
    </bndbox>
    <attributes>
      <attribute>
        <name>rotation</name>
        <value>0.0</value>
      </attribute>
    </attributes>
  </object>
  <object>
    <name>truck-s-</name>
    <truncated>0</truncated>
    <occluded>0</occluded>
    <difficult>0</difficult>
    <bndbox>
      <xmin>29.78</xmin>
      <ymin>222.18</ymin>
      <xmax>76.61</xmax>
      <ymax>276.36</ymax>
    </bndbox>
    <attributes>
      <attribute>
        <name>rotation</name>
        <value>0.0</value>
      </attribute>
    </attributes>
  </object>
  <object>
    <name>car</name>
    <truncated>0</truncated>
    <occluded>0</occluded>
    <difficult>0</difficult>
    <bndbox>
      <xmin>297.35</xmin>
      <ymin>170.94</ymin>
      <xmax>320.54</xmax>
      <ymax>191.95</ymax>
    </bndbox>
    <attributes>
      <attribute>
        <name>rotation</name>
        <value>0.0</value>
      </attribute>
    </attributes>
  </object>
  <object>
    <name>car</name>
    <truncated>0</truncated>
    <occluded>0</occluded>
    <difficult>0</difficult>
    <bndbox>
      <xmin>222.03</xmin>
      <ymin>173.61</ymin>
      <xmax>246.14</xmax>
      <ymax>198.37</ymax>
    </bndbox>
    <attributes>
      <attribute>
        <name>rotation</name>
        <value>0.0</value>
      </attribute>
    </attributes>
  </object>
  <object>
    <name>car</name>
    <truncated>0</truncated>
    <occluded>0</occluded>
    <difficult>0</difficult>
    <bndbox>
      <xmin>213.56</xmin>
      <ymin>204.81</ymin>
      <xmax>245.34</xmax>
      <ymax>234.21</ymax>
    </bndbox>
    <attributes>
      <attribute>
        <name>rotation</name>
        <value>0.0</value>
      </attribute>
    </attributes>
  </object>
  <object>
    <name>car</name>
    <truncated>0</truncated>
    <occluded>0</occluded>
    <difficult>0</difficult>
    <bndbox>
      <xmin>161.94</xmin>
      <ymin>274.68</ymin>
      <xmax>221.72</xmax>
      <ymax>330.11</ymax>
    </bndbox>
    <attributes>
      <attribute>
        <name>rotation</name>
        <value>0.0</value>
      </attribute>
    </attributes>
  </object>
  <object>
    <name>small truck</name>
    <truncated>0</truncated>
    <occluded>0</occluded>
    <difficult>0</difficult>
    <bndbox>
      <xmin>158.94</xmin>
      <ymin>171.67</ymin>
      <xmax>205.61</xmax>
      <ymax>220.38</ymax>
    </bndbox>
    <attributes>
      <attribute>
        <name>rotation</name>
        <value>0.0</value>
      </attribute>
    </attributes>
  </object>
  <object>
    <name>car</name>
    <truncated>0</truncated>
    <occluded>0</occluded>
    <difficult>0</difficult>
    <bndbox>
      <xmin>335.21</xmin>
      <ymin>257.09</ymin>
      <xmax>386.67</xmax>
      <ymax>312.11</ymax>
    </bndbox>
    <attributes>
      <attribute>
        <name>rotation</name>
        <value>0.0</value>
      </attribute>
    </attributes>
  </object>
</annotation>
