<annotation>
  <folder>malam</folder>
  <filename>malam_04112021_mp4-346_jpg.rf.e6fce47bdae5c33e78d0ee8a8cfb8c32.jpg</filename>
  <source>
    <database>Unknown</database>
    <annotation>Unknown</annotation>
    <image>Unknown</image>
  </source>
  <size>
    <width>640</width>
    <height>480</height>
    <depth></depth>
  </size>
  <segmented>0</segmented>
  <object>
    <name>car</name>
    <truncated>0</truncated>
    <occluded>0</occluded>
    <difficult>0</difficult>
    <bndbox>
      <xmin>319.23</xmin>
      <ymin>231.93</ymin>
      <xmax>351.66</xmax>
      <ymax>266.32</ymax>
    </bndbox>
    <attributes>
      <attribute>
        <name>rotation</name>
        <value>0.0</value>
      </attribute>
    </attributes>
  </object>
  <object>
    <name>truck-l-</name>
    <truncated>0</truncated>
    <occluded>0</occluded>
    <difficult>0</difficult>
    <bndbox>
      <xmin>361.77</xmin>
      <ymin>205.3</ymin>
      <xmax>413.55</xmax>
      <ymax>270.55</ymax>
    </bndbox>
    <attributes>
      <attribute>
        <name>rotation</name>
        <value>0.0</value>
      </attribute>
    </attributes>
  </object>
  <object>
    <name>truck-xl-</name>
    <truncated>0</truncated>
    <occluded>0</occluded>
    <difficult>0</difficult>
    <bndbox>
      <xmin>363.64</xmin>
      <ymin>205.81</ymin>
      <xmax>412.49</xmax>
      <ymax>270.35</ymax>
    </bndbox>
    <attributes>
      <attribute>
        <name>rotation</name>
        <value>0.0</value>
      </attribute>
    </attributes>
  </object>
  <object>
    <name>car</name>
    <truncated>0</truncated>
    <occluded>0</occluded>
    <difficult>0</difficult>
    <bndbox>
      <xmin>311.97</xmin>
      <ymin>199.32</ymin>
      <xmax>333.89</xmax>
      <ymax>220.73</ymax>
    </bndbox>
    <attributes>
      <attribute>
        <name>rotation</name>
        <value>0.0</value>
      </attribute>
    </attributes>
  </object>
</annotation>
