<annotation>
	<folder></folder>
	<filename>IMG_20220316_143005_jpg.rf.c4b44dac322fc7234137684204bc59e3.jpg</filename>
	<path>IMG_20220316_143005_jpg.rf.c4b44dac322fc7234137684204bc59e3.jpg</path>
	<source>
		<database>roboflow.ai</database>
	</source>
	<size>
		<width>960</width>
		<height>720</height>
		<depth>3</depth>
	</size>
	<segmented>0</segmented>
	<object>
		<name>A Hearts</name>
		<pose>Unspecified</pose>
		<truncated>0</truncated>
		<difficult>0</difficult>
		<occluded>0</occluded>
		<bndbox>
			<xmin>516</xmin>
			<xmax>730</xmax>
			<ymin>150</ymin>
			<ymax>441</ymax>
		</bndbox>
	</object>
	<object>
		<name>2 Diamonds</name>
		<pose>Unspecified</pose>
		<truncated>0</truncated>
		<difficult>0</difficult>
		<occluded>0</occluded>
		<bndbox>
			<xmin>86</xmin>
			<xmax>320</xmax>
			<ymin>172</ymin>
			<ymax>473</ymax>
		</bndbox>
	</object>
	<object>
		<name>3 Diamonds</name>
		<pose>Unspecified</pose>
		<truncated>0</truncated>
		<difficult>0</difficult>
		<occluded>0</occluded>
		<bndbox>
			<xmin>310</xmin>
			<xmax>521</xmax>
			<ymin>170</ymin>
			<ymax>467</ymax>
		</bndbox>
	</object>
	<object>
		<name>4 Diamonds</name>
		<pose>Unspecified</pose>
		<truncated>0</truncated>
		<difficult>0</difficult>
		<occluded>0</occluded>
		<bndbox>
			<xmin>716</xmin>
			<xmax>919</xmax>
			<ymin>133</ymin>
			<ymax>430</ymax>
		</bndbox>
	</object>
</annotation>
