<annotation>
	<folder></folder>
	<filename>IMG_20220316_140519_jpg.rf.1b5098a2ad305e7147f2ac8c179c6154.jpg</filename>
	<path>IMG_20220316_140519_jpg.rf.1b5098a2ad305e7147f2ac8c179c6154.jpg</path>
	<source>
		<database>roboflow.ai</database>
	</source>
	<size>
		<width>960</width>
		<height>720</height>
		<depth>3</depth>
	</size>
	<segmented>0</segmented>
	<object>
		<name>6 Spades</name>
		<pose>Unspecified</pose>
		<truncated>0</truncated>
		<difficult>0</difficult>
		<occluded>0</occluded>
		<bndbox>
			<xmin>272</xmin>
			<xmax>557</xmax>
			<ymin>49</ymin>
			<ymax>251</ymax>
		</bndbox>
	</object>
	<object>
		<name>7 Spades</name>
		<pose>Unspecified</pose>
		<truncated>0</truncated>
		<difficult>0</difficult>
		<occluded>0</occluded>
		<bndbox>
			<xmin>515</xmin>
			<xmax>776</xmax>
			<ymin>242</ymin>
			<ymax>427</ymax>
		</bndbox>
	</object>
	<object>
		<name>5 Hearts</name>
		<pose>Unspecified</pose>
		<truncated>0</truncated>
		<difficult>0</difficult>
		<occluded>0</occluded>
		<bndbox>
			<xmin>213</xmin>
			<xmax>499</xmax>
			<ymin>289</ymin>
			<ymax>480</ymax>
		</bndbox>
	</object>
	<object>
		<name>8 Spades</name>
		<pose>Unspecified</pose>
		<truncated>0</truncated>
		<difficult>0</difficult>
		<occluded>0</occluded>
		<bndbox>
			<xmin>237</xmin>
			<xmax>519</xmax>
			<ymin>487</ymin>
			<ymax>703</ymax>
		</bndbox>
	</object>
</annotation>
