<annotation>
	<folder></folder>
	<filename>IMG_20220316_165623_jpg.rf.bbe7a814e66233c2e992e5e2bdb3ba96.jpg</filename>
	<path>IMG_20220316_165623_jpg.rf.bbe7a814e66233c2e992e5e2bdb3ba96.jpg</path>
	<source>
		<database>roboflow.ai</database>
	</source>
	<size>
		<width>960</width>
		<height>720</height>
		<depth>3</depth>
	</size>
	<segmented>0</segmented>
	<object>
		<name>9 Diamonds</name>
		<pose>Unspecified</pose>
		<truncated>0</truncated>
		<difficult>0</difficult>
		<occluded>0</occluded>
		<bndbox>
			<xmin>447</xmin>
			<xmax>679</xmax>
			<ymin>100</ymin>
			<ymax>340</ymax>
		</bndbox>
	</object>
	<object>
		<name>59</name>
		<pose>Unspecified</pose>
		<truncated>0</truncated>
		<difficult>0</difficult>
		<occluded>0</occluded>
		<bndbox>
			<xmin>91</xmin>
			<xmax>391</xmax>
			<ymin>288</ymin>
			<ymax>685</ymax>
		</bndbox>
	</object>
	<object>
		<name>J Diamonds</name>
		<pose>Unspecified</pose>
		<truncated>0</truncated>
		<difficult>0</difficult>
		<occluded>0</occluded>
		<bndbox>
			<xmin>588</xmin>
			<xmax>801</xmax>
			<ymin>326</ymin>
			<ymax>614</ymax>
		</bndbox>
	</object>
	<object>
		<name>Q Diamonds</name>
		<pose>Unspecified</pose>
		<truncated>0</truncated>
		<difficult>0</difficult>
		<occluded>0</occluded>
		<bndbox>
			<xmin>249</xmin>
			<xmax>512</xmax>
			<ymin>45</ymin>
			<ymax>307</ymax>
		</bndbox>
	</object>
	<object>
		<name>K Diamonds</name>
		<pose>Unspecified</pose>
		<truncated>0</truncated>
		<difficult>0</difficult>
		<occluded>0</occluded>
		<bndbox>
			<xmin>356</xmin>
			<xmax>620</xmax>
			<ymin>349</ymin>
			<ymax>700</ymax>
		</bndbox>
	</object>
</annotation>
