<annotation>
	<folder></folder>
	<filename>IMG_20220316_140325_jpg.rf.34568f44e429996e88f9e35b57b0d922.jpg</filename>
	<path>IMG_20220316_140325_jpg.rf.34568f44e429996e88f9e35b57b0d922.jpg</path>
	<source>
		<database>roboflow.ai</database>
	</source>
	<size>
		<width>960</width>
		<height>720</height>
		<depth>3</depth>
	</size>
	<segmented>0</segmented>
	<object>
		<name>5 Hearts</name>
		<pose>Unspecified</pose>
		<truncated>0</truncated>
		<difficult>0</difficult>
		<occluded>0</occluded>
		<bndbox>
			<xmin>382</xmin>
			<xmax>595</xmax>
			<ymin>28</ymin>
			<ymax>177</ymax>
		</bndbox>
	</object>
	<object>
		<name>8 Spades</name>
		<pose>Unspecified</pose>
		<truncated>0</truncated>
		<difficult>0</difficult>
		<occluded>0</occluded>
		<bndbox>
			<xmin>382</xmin>
			<xmax>596</xmax>
			<ymin>214</ymin>
			<ymax>384</ymax>
		</bndbox>
	</object>
	<object>
		<name>6 Spades</name>
		<pose>Unspecified</pose>
		<truncated>0</truncated>
		<difficult>0</difficult>
		<occluded>0</occluded>
		<bndbox>
			<xmin>424</xmin>
			<xmax>623</xmax>
			<ymin>380</ymin>
			<ymax>523</ymax>
		</bndbox>
	</object>
	<object>
		<name>7 Spades</name>
		<pose>Unspecified</pose>
		<truncated>0</truncated>
		<difficult>0</difficult>
		<occluded>0</occluded>
		<bndbox>
			<xmin>448</xmin>
			<xmax>665</xmax>
			<ymin>541</ymin>
			<ymax>709</ymax>
		</bndbox>
	</object>
</annotation>
