<annotation>
	<folder></folder>
	<filename>IMG_20220316_161418_jpg.rf.3d92d9f9298e31457777e005ef27671b.jpg</filename>
	<path>IMG_20220316_161418_jpg.rf.3d92d9f9298e31457777e005ef27671b.jpg</path>
	<source>
		<database>roboflow.ai</database>
	</source>
	<size>
		<width>960</width>
		<height>720</height>
		<depth>3</depth>
	</size>
	<segmented>0</segmented>
	<object>
		<name>9 Hearts</name>
		<pose>Unspecified</pose>
		<truncated>0</truncated>
		<difficult>0</difficult>
		<occluded>0</occluded>
		<bndbox>
			<xmin>173</xmin>
			<xmax>371</xmax>
			<ymin>318</ymin>
			<ymax>631</ymax>
		</bndbox>
	</object>
	<object>
		<name>10 Diamonds</name>
		<pose>Unspecified</pose>
		<truncated>0</truncated>
		<difficult>0</difficult>
		<occluded>0</occluded>
		<bndbox>
			<xmin>325</xmin>
			<xmax>584</xmax>
			<ymin>374</ymin>
			<ymax>716</ymax>
		</bndbox>
	</object>
	<object>
		<name>J Hearts</name>
		<pose>Unspecified</pose>
		<truncated>0</truncated>
		<difficult>0</difficult>
		<occluded>0</occluded>
		<bndbox>
			<xmin>304</xmin>
			<xmax>534</xmax>
			<ymin>59</ymin>
			<ymax>336</ymax>
		</bndbox>
	</object>
	<object>
		<name>Q Hearts</name>
		<pose>Unspecified</pose>
		<truncated>0</truncated>
		<difficult>0</difficult>
		<occluded>0</occluded>
		<bndbox>
			<xmin>498</xmin>
			<xmax>838</xmax>
			<ymin>71</ymin>
			<ymax>452</ymax>
		</bndbox>
	</object>
	<object>
		<name>K Hearts</name>
		<pose>Unspecified</pose>
		<truncated>0</truncated>
		<difficult>0</difficult>
		<occluded>0</occluded>
		<bndbox>
			<xmin>163</xmin>
			<xmax>348</xmax>
			<ymin>66</ymin>
			<ymax>305</ymax>
		</bndbox>
	</object>
</annotation>
